PostgresqlDoc/README.md
PostgresqlDoc/__init__.py
PostgresqlDoc/__main__.py
PostgresqlDoc/file.epub
PostgresqlDoc/index.html
PostgresqlDoc/css/__init__.py
PostgresqlDoc/css/annotations.css
PostgresqlDoc/css/main.css
PostgresqlDoc/css/normalize.css
PostgresqlDoc/css/popup.css
PostgresqlDoc/font/__init__.py
PostgresqlDoc/font/fontello.eot
PostgresqlDoc/font/fontello.svg
PostgresqlDoc/font/fontello.ttf
PostgresqlDoc/font/fontello.woff
PostgresqlDoc/img/__init__.py
PostgresqlDoc/img/annotator-glyph-sprite.png
PostgresqlDoc/img/annotator-icon-sprite.png
PostgresqlDoc/img/apple-touch-icon.png
PostgresqlDoc/img/cancelfullscreen.png
PostgresqlDoc/img/close.png
PostgresqlDoc/img/fullscreen.png
PostgresqlDoc/img/loader.gif
PostgresqlDoc/img/menu-icon.png
PostgresqlDoc/img/save.png
PostgresqlDoc/img/saved.png
PostgresqlDoc/img/settings-s.png
PostgresqlDoc/img/settings.png
PostgresqlDoc/img/star.png
PostgresqlDoc/js/__init__.py
PostgresqlDoc/js/epub.js
PostgresqlDoc/js/epub.min.js
PostgresqlDoc/js/epub.min.map
PostgresqlDoc/js/hooks.min.js
PostgresqlDoc/js/hooks.min.map
PostgresqlDoc/js/reader.js
PostgresqlDoc/js/reader.js.map
PostgresqlDoc/js/reader.min.js
PostgresqlDoc/js/reader.min.map
PostgresqlDoc/js/hooks/__init__.py
PostgresqlDoc/js/hooks/extensions/__init__.py
PostgresqlDoc/js/hooks/extensions/highlight.js
PostgresqlDoc/js/libs/__init__.py
PostgresqlDoc/js/libs/jquery.min.js
PostgresqlDoc/js/libs/localforage.min.js
PostgresqlDoc/js/libs/screenfull.js
PostgresqlDoc/js/libs/screenfull.min.js
PostgresqlDoc/js/libs/zip.min.js
PostgresqlDoc/js/plugins/__init__.py
PostgresqlDoc/js/plugins/hypothesis.js
PostgresqlDoc/js/plugins/search.js
postgresql_doc-2024.3.2.0.dist-info/METADATA
postgresql_doc-2024.3.2.0.dist-info/WHEEL
postgresql_doc-2024.3.2.0.dist-info/entry_points.txt
postgresql_doc-2024.3.2.0.dist-info/top_level.txt
postgresql_doc-2024.3.2.0.dist-info/RECORD
